tdrpa/bot.exe
tdrpa/tdcore.cp38-win_amd64.pyd
tdrpa/tdcore/LocatorBrowser.pyi
tdrpa/tdcore/LocatorWindows.pyi
tdrpa/tdcore/__init__.pyi
tdrpa/tdcore/exception.pyi
tdrpa/tdcore/log/__init__.pyi
tdrpa/tdcore/log/log.pyi
tdrpa/tdcore/util/__init__.pyi
tdrpa/tdcore/util/hotkey.pyi
tdrpa/tdcore-license/LICENSE
tdrpa/tdcore-license/infi.systray/LICENSE.txt
tdrpa/tdcore-license/playwright/LICENSE
tdrpa/tdcore-license/psutil/LICENSE.txt
tdrpa/tdcore-license/pynput/COPYING.LGPL
tdrpa/tdcore-license/requests/LICENSE.txt
tdrpa/tdcore-license/tzlocal/LICENSE.txt
tdrpa/tdcore-license/uiautomation/LICENSE.txt
tdrpa_tdcore-1.2.22.dist-info/METADATA
tdrpa_tdcore-1.2.22.dist-info/WHEEL
tdrpa_tdcore-1.2.22.dist-info/top_level.txt
tdrpa_tdcore-1.2.22.dist-info/RECORD
